
{
    "app-id": "de.uchuujin.fp.termzoo.kitty0_21_1",
    "runtime": "org.gnome.Platform",
    "runtime-version": "3.36",
    "sdk": "org.gnome.Sdk",
    "command": "kitty",
    "finish-args": [ "--socket=x11", "--socket=wayland", "--device=dri", "--talk-name=org.freedesktop.Flatpak"],
    "modules": [
        {
            "name": "kitty",
            "buildsystem": "simple",
            "build-commands": [
                "python3 setup.py linux-package",
                "cp -r linux-package/* /app"
            ],
            "sources": [
                {
                    "type": "archive",
                    "url": "https://github.com/kovidgoyal/kitty/releases/download/v0.21.1/kitty-0.21.1.tar.xz",
                    "sha512": "86b1e03f8227375cc46dabffd972a131c8a33d55d87888b2cf67d97da6749144408778b8ac126dbc29fe3850f272e5ae0c4313194ebb130ae3417b04b76cb987"
                }
            ]
        },
        {
            "name": "scripts",
            "buildsystem": "simple",
            "build-commands": [
                "install -D run-in-host /app/bin/run-in-host"
            ],
            "sources": [
                {
                    "type": "file",
                    "path": "../run-in-host"
                }
            ]
        }
    ]
}
